procgen_yukun-0.10.8.dist-info/RECORD
procgen_yukun-0.10.8.dist-info/WHEEL
procgen_yukun-0.10.8.dist-info/METADATA
procgen_yukun-0.10.8.dist-info/LICENSE
procgen_yukun-0.10.8.dist-info/top_level.txt
procgen/builder.py
procgen/env_test.py
procgen/state_test.py
procgen/interactive.py
procgen/__init__.py
procgen/env.py
procgen/gym_registration.py
procgen/version.txt
procgen/data/prebuilt/libenv.so
procgen/data/assets/space_backgrounds/eye_nebula_01.png
procgen/data/assets/space_backgrounds/Background-1.png
procgen/data/assets/space_backgrounds/ez_space_lite_01.png
procgen/data/assets/space_backgrounds/parallax-space-backgound.png
procgen/data/assets/space_backgrounds/meyespace_v1_01.png
procgen/data/assets/space_backgrounds/deep_sky_01.png
procgen/data/assets/space_backgrounds/space_nebula_01.png
procgen/data/assets/space_backgrounds/deep_space_01.png
procgen/data/assets/space_backgrounds/Background-2.png
procgen/data/assets/space_backgrounds/milky_way_01.png
procgen/data/assets/space_backgrounds/Background-3.png
procgen/data/assets/space_backgrounds/Background-4.png
procgen/data/assets/space_backgrounds/spacegen_01.png
procgen/data/assets/platform_backgrounds_2/candy3.png
procgen/data/assets/platform_backgrounds_2/fantasy3.png
procgen/data/assets/platform_backgrounds_2/beach4.png
procgen/data/assets/platform_backgrounds_2/fantasy2.png
procgen/data/assets/platform_backgrounds_2/candy4.png
procgen/data/assets/platform_backgrounds_2/fantasy1.png
procgen/data/assets/platform_backgrounds_2/beach3.png
procgen/data/assets/platform_backgrounds_2/beach1.png
procgen/data/assets/platform_backgrounds_2/fantasy4.png
procgen/data/assets/platform_backgrounds_2/candy1.png
procgen/data/assets/platform_backgrounds_2/candy2.png
procgen/data/assets/platform_backgrounds_2/beach2.png
procgen/data/assets/water_backgrounds/underwater2.png
procgen/data/assets/water_backgrounds/water3.png
procgen/data/assets/water_backgrounds/water4.png
procgen/data/assets/water_backgrounds/underwater1.png
procgen/data/assets/water_backgrounds/water1.png
procgen/data/assets/water_backgrounds/water2.png
procgen/data/assets/water_backgrounds/underwater3.png
